{"pandas": [1, "/categories/pandas.html", {"posts": [{"title": "nikoladu", "isodate": "2015-09-02T21:47:00+00:00", "date": "09/02/2015", "url": "/posts/nikoladu.html"}]}], "nikola": [2, "/categories/nikola.html", {"posts": [{"title": "niktrans", "isodate": "2015-09-09T11:41:01+00:00", "date": "09/09/2015", "url": "/posts/niktrans.html"}, {"title": "nikoladu", "isodate": "2015-09-02T21:47:00+00:00", "date": "09/02/2015", "url": "/posts/nikoladu.html"}]}], "python": [2, "/categories/python.html", {"posts": [{"title": "niktrans", "isodate": "2015-09-09T11:41:01+00:00", "date": "09/09/2015", "url": "/posts/niktrans.html"}, {"title": "brobeurtweet", "isodate": "2015-08-28T21:33:21+00:00", "date": "08/28/2015", "url": "/posts/brobeurtweet.html"}]}], "json": [1, "/categories/json.html", {"posts": [{"title": "nikoladu", "isodate": "2015-09-02T21:47:00+00:00", "date": "09/02/2015", "url": "/posts/nikoladu.html"}]}], "rsync": [1, "/categories/rsync.html", {"posts": [{"title": "niktrans", "isodate": "2015-09-09T11:41:01+00:00", "date": "09/09/2015", "url": "/posts/niktrans.html"}]}], "os": [1, "/categories/os.html", {"posts": [{"title": "niktrans", "isodate": "2015-09-09T11:41:01+00:00", "date": "09/09/2015", "url": "/posts/niktrans.html"}]}], "twitter": [1, "/categories/twitter.html", {"posts": [{"title": "brobeurtweet", "isodate": "2015-08-28T21:33:21+00:00", "date": "08/28/2015", "url": "/posts/brobeurtweet.html"}]}]}